embed/__init__.py
embed/_infer.py
embed/py.typed
embed-0.3.0.dist-info/METADATA
embed-0.3.0.dist-info/WHEEL
embed-0.3.0.dist-info/RECORD
