Metadata-Version: 2.1
Name: embed
Version: 0.3.0
Summary: A stable, fast and easy-to-use inference library with a focus on a sync-to-async API
Home-page: https://github.com/michaelfeil/infinity
Keywords: vector,embedding,neural,search,sentence-transformers
Author: michaelfeil
Author-email: me@michaelfeil.eu
Requires-Python: >=3.9,<4
Classifier: Programming Language :: Python :: 3
Classifier: Programming Language :: Python :: 3.9
Classifier: Programming Language :: Python :: 3.10
Classifier: Programming Language :: Python :: 3.11
Classifier: Programming Language :: Python :: 3.12
Requires-Dist: infinity_emb[audio,optimum,torch,vision] (==0.0.58)
Project-URL: Repository, https://github.com/michaelfeil/infinity
